{
  "__data_type": "ITP ",
  "MAIN": {
    "type": "list",
    "value": [
      {
        "__struct_id": 0,
        "ID": {
          "type": "byte",
          "value": 0
        },
        "LIST": {
          "type": "list",
          "value": [
            {
              "__struct_id": 0,
              "RESREF": {
                "type": "resref",
                "value": "aby01_o07_01"
              },
              "STRREF": {
                "type": "dword",
                "value": 63678
              }
            },
            {
              "__struct_id": 0,
              "RESREF": {
                "type": "resref",
                "value": "aby01_o05_01"
              },
              "STRREF": {
                "type": "dword",
                "value": 63719
              }
            },
            {
              "__struct_id": 0,
              "RESREF": {
                "type": "resref",
                "value": "aby01_q05_01"
              },
              "STRREF": {
                "type": "dword",
                "value": 63705
              }
            },
            {
              "__struct_id": 0,
              "RESREF": {
                "type": "resref",
                "value": "aby01_p07_01"
              },
              "STRREF": {
                "type": "dword",
                "value": 63711
              }
            },
            {
              "__struct_id": 0,
              "RESREF": {
                "type": "resref",
                "value": "aby01_q06_01"
              },
              "STRREF": {
                "type": "dword",
                "value": 63699
              }
            },
            {
              "__struct_id": 0,
              "RESREF": {
                "type": "resref",
                "value": "aby01_p05_01"
              },
              "STRREF": {
                "type": "dword",
                "value": 63636
              }
            },
            {
              "__struct_id": 0,
              "RESREF": {
                "type": "resref",
                "value": "aby01_u12_01"
              },
              "STRREF": {
                "type": "dword",
                "value": 63686
              }
            },
            {
              "__struct_id": 0,
              "RESREF": {
                "type": "resref",
                "value": "aby01_u14_01"
              },
              "STRREF": {
                "type": "dword",
                "value": 63716
              }
            },
            {
              "__struct_id": 0,
              "RESREF": {
                "type": "resref",
                "value": "aby01_v14_01"
              },
              "STRREF": {
                "type": "dword",
                "value": 63717
              }
            },
            {
              "__struct_id": 0,
              "RESREF": {
                "type": "resref",
                "value": "aby01_g17_01"
              },
              "STRREF": {
                "type": "dword",
                "value": 63333
              }
            },
            {
              "__struct_id": 0,
              "RESREF": {
                "type": "resref",
                "value": "aby01_h17_01"
              },
              "STRREF": {
                "type": "dword",
                "value": 63363
              }
            },
            {
              "__struct_id": 0,
              "RESREF": {
                "type": "resref",
                "value": "aby01_i17_01"
              },
              "STRREF": {
                "type": "dword",
                "value": 63713
              }
            },
            {
              "__struct_id": 0,
              "RESREF": {
                "type": "resref",
                "value": "aby01_j17_01"
              },
              "STRREF": {
                "type": "dword",
                "value": 63715
              }
            },
            {
              "__struct_id": 0,
              "RESREF": {
                "type": "resref",
                "value": "aby01_h02_03"
              },
              "STRREF": {
                "type": "dword",
                "value": 63701
              }
            },
            {
              "__struct_id": 0,
              "RESREF": {
                "type": "resref",
                "value": "aby01_h18_01"
              },
              "STRREF": {
                "type": "dword",
                "value": 63712
              }
            },
            {
              "__struct_id": 0,
              "RESREF": {
                "type": "resref",
                "value": "aby01_h19_01"
              },
              "STRREF": {
                "type": "dword",
                "value": 63714
              }
            },
            {
              "__struct_id": 0,
              "RESREF": {
                "type": "resref",
                "value": "aby01_u01_01"
              },
              "STRREF": {
                "type": "dword",
                "value": 63662
              }
            },
            {
              "__struct_id": 0,
              "RESREF": {
                "type": "resref",
                "value": "aby01_o10_01"
              },
              "STRREF": {
                "type": "dword",
                "value": 63689
              }
            },
            {
              "__struct_id": 0,
              "RESREF": {
                "type": "resref",
                "value": "aby01_o10_02"
              },
              "STRREF": {
                "type": "dword",
                "value": 63690
              }
            },
            {
              "__struct_id": 0,
              "RESREF": {
                "type": "resref",
                "value": "aby01_o10_03"
              },
              "STRREF": {
                "type": "dword",
                "value": 63691
              }
            },
            {
              "__struct_id": 0,
              "RESREF": {
                "type": "resref",
                "value": "aby01_o10_04"
              },
              "STRREF": {
                "type": "dword",
                "value": 63692
              }
            },
            {
              "__struct_id": 0,
              "RESREF": {
                "type": "resref",
                "value": "aby01_o10_05"
              },
              "STRREF": {
                "type": "dword",
                "value": 63693
              }
            },
            {
              "__struct_id": 0,
              "RESREF": {
                "type": "resref",
                "value": "aby01_o11_01"
              },
              "STRREF": {
                "type": "dword",
                "value": 63706
              }
            },
            {
              "__struct_id": 0,
              "RESREF": {
                "type": "resref",
                "value": "aby01_o12_01"
              },
              "STRREF": {
                "type": "dword",
                "value": 63697
              }
            },
            {
              "__struct_id": 0,
              "RESREF": {
                "type": "resref",
                "value": "aby01_o14_01"
              },
              "STRREF": {
                "type": "dword",
                "value": 63698
              }
            },
            {
              "__struct_id": 0,
              "RESREF": {
                "type": "resref",
                "value": "aby01_o13_01"
              },
              "STRREF": {
                "type": "dword",
                "value": 68816
              }
            },
            {
              "__struct_id": 0,
              "RESREF": {
                "type": "resref",
                "value": "aby01_k17_01"
              },
              "STRREF": {
                "type": "dword",
                "value": 63309
              }
            },
            {
              "__struct_id": 0,
              "RESREF": {
                "type": "resref",
                "value": "aby01_r10_01"
              },
              "STRREF": {
                "type": "dword",
                "value": 63677
              }
            },
            {
              "__struct_id": 0,
              "RESREF": {
                "type": "resref",
                "value": "tall_a01_01"
              },
              "STRREF": {
                "type": "dword",
                "value": 63362
              }
            },
            {
              "__struct_id": 0,
              "RESREF": {
                "type": "resref",
                "value": "tall_b01_01"
              },
              "STRREF": {
                "type": "dword",
                "value": 63315
              }
            },
            {
              "__struct_id": 0,
              "RESREF": {
                "type": "resref",
                "value": "aby01_o13_02"
              },
              "STRREF": {
                "type": "dword",
                "value": 68816
              }
            }
          ]
        },
        "STRREF": {
          "type": "dword",
          "value": 63261
        }
      },
      {
        "__struct_id": 0,
        "ID": {
          "type": "byte",
          "value": 1
        },
        "LIST": {
          "type": "list",
          "value": [
            {
              "__struct_id": 0,
              "RESREF": {
                "type": "resref",
                "value": "aby01_o06_01"
              },
              "STRREF": {
                "type": "dword",
                "value": 63637
              }
            },
            {
              "__struct_id": 0,
              "RESREF": {
                "type": "resref",
                "value": "aby01_u04_01"
              },
              "STRREF": {
                "type": "dword",
                "value": 63707
              }
            },
            {
              "__struct_id": 0,
              "RESREF": {
                "type": "resref",
                "value": "aby01_u13_01"
              },
              "STRREF": {
                "type": "dword",
                "value": 63718
              }
            },
            {
              "__struct_id": 0,
              "RESREF": {
                "type": "resref",
                "value": "aby01_s18_01"
              },
              "STRREF": {
                "type": "dword",
                "value": 63676
              }
            },
            {
              "__struct_id": 0,
              "RESREF": {
                "type": "resref",
                "value": "aby01_s19_01"
              },
              "STRREF": {
                "type": "dword",
                "value": 63710
              }
            },
            {
              "__struct_id": 0,
              "RESREF": {
                "type": "resref",
                "value": "aby01_u06_01"
              },
              "STRREF": {
                "type": "dword",
                "value": 63708
              }
            },
            {
              "__struct_id": 0,
              "RESREF": {
                "type": "resref",
                "value": "aby01_u09_01"
              },
              "STRREF": {
                "type": "dword",
                "value": 63709
              }
            },
            {
              "__struct_id": 0,
              "RESREF": {
                "type": "resref",
                "value": "vwt01_a01"
              },
              "STRREF": {
                "type": "dword",
                "value": 111536
              }
            },
            {
              "__struct_id": 0,
              "RESREF": {
                "type": "resref",
                "value": "vwt01_b01"
              },
              "STRREF": {
                "type": "dword",
                "value": 111553
              }
            }
          ]
        },
        "STRREF": {
          "type": "dword",
          "value": 63262
        }
      },
      {
        "__struct_id": 0,
        "ID": {
          "type": "byte",
          "value": 2
        },
        "LIST": {
          "type": "list",
          "value": [
            {
              "__struct_id": 0,
              "RESREF": {
                "type": "resref",
                "value": "floor"
              },
              "STRREF": {
                "type": "dword",
                "value": 63459
              }
            },
            {
              "__struct_id": 0,
              "RESREF": {
                "type": "resref",
                "value": "lava"
              },
              "STRREF": {
                "type": "dword",
                "value": 63493
              }
            },
            {
              "__struct_id": 0,
              "RESREF": {
                "type": "resref",
                "value": "stream"
              },
              "STRREF": {
                "type": "dword",
                "value": 63302
              }
            },
            {
              "__struct_id": 0,
              "RESREF": {
                "type": "resref",
                "value": "wall1"
              },
              "STRREF": {
                "type": "dword",
                "value": 63671
              }
            },
            {
              "__struct_id": 0,
              "RESREF": {
                "type": "resref",
                "value": "wall2"
              },
              "STRREF": {
                "type": "dword",
                "value": 63672
              }
            },
            {
              "__struct_id": 0,
              "RESREF": {
                "type": "resref",
                "value": "road"
              },
              "STRREF": {
                "type": "dword",
                "value": 63641
              }
            },
            {
              "__struct_id": 0,
              "RESREF": {
                "type": "resref",
                "value": "eraser"
              },
              "STRREF": {
                "type": "dword",
                "value": 63291
              }
            },
            {
              "__struct_id": 0,
              "RESREF": {
                "type": "resref",
                "value": "raiselower"
              },
              "STRREF": {
                "type": "dword",
                "value": 63292
              }
            }
          ]
        },
        "STRREF": {
          "type": "dword",
          "value": 8282
        }
      }
    ]
  }
}
